{
  "project_name": "대용량 자료전송시스템 고도화",
  "agency": "국방과학연구소",
  "purpose": "연구데이터 용량 증가에 따른 자료전송 용량 및 방안 개선, 안전메일 이용 절차의 사용성 개선, 감사기록 및 계정관리 등 보안기능 보강, 노후 인프라 교체에 따른 재연동 및 데이터 이관",
  "budget": "입찰공고문 참조",
  "contract_type": "제한경쟁입찰, 협상에 의한 계약",
  "deadline": "입찰공고문 참조",
  "duration": "계약일로부터 5개월 이내",
  "requirements_must": "기밀보안 체계 및 대책, 저작권 존중여부 명시, 시스템 보안성 확보방안과 개인정보보호 대책 제시; 투입인력 신원조사 및 보안서약서 제출; 사업관련 자료의 외부 저장 및 전송 금지; 주기적 자체 보안교육 및 보안확약서 제출",
  "eval_items": "기술능력 평가 및 입찰가격 평가(기술능력 90%, 가격평가 10%); 기술성 평가는 소프트웨어 기술성 평가기준 및 협상에 의한 계약 제안서평가 세부기준에 따름",
  "price_eval": "협상에 의한 계약 체결기준에 따름(종합평가로 우선협상대상자 선정), 가격평가 비중 10%",
  "eligibility": "입찰공고문 및 중소기업제품 구매촉진법에 따라 직접생산이 가능한 업체(중소기업 기준)",
  "scope_custom": "신규 자료송수신체계 도입 및 관련 세부사항(자료송수신체계 및 하자보수 계획 포함)",
  "improvement_email": "안전메일의 서비스 이용 절차 개선으로 인한 사용성 향상",
  "response_time": "NOT_FOUND",
  "security": "기밀보안 체계 및 대책 수립, 개인정보보호 대책, 사업관련 자료의 외부 저장·전송 금지, 투입인력 신원조사 및 보안서약서 제출",
  "warranty_duration": "하자보수 계획 명시(하자보수 기간 명시값은 CONTEXT에 없음)",
  "restriction": "계약법령·유의서 위반자 및 부정행위자 등 입찰무효 사유 적용; 입찰공고문에 따름",
  "eval_ratio": "기술능력 90%, 가격평가 10%",
  "development_methodology": "제안서에 개발 방법론 제시(요구사항 STA-02: 개발 방법론 제시)",
  "max_transfer": "NOT_FOUND",
  "concurrent_users": "NOT_FOUND"
}