{
  "project_name": "고양도시관리공사 관산근린공원 다목적구장 회원 통합운영관리 시스템 구축",
  "agency": "고양도시관리공사",
  "purpose": "NOT_FOUND",
  "budget": "90,000,000 원",
  "contract_type": "제한경쟁입찰 ( 협상에 의한 계약",
  "deadline": "NOT_FOUND",
  "duration": "착수일로부터 90 일",
  "requirements_must": "시스템 구축에 필요한 운영환경·보안·시스템 구성요건 및 제안요구사항에 따른 기능·성능 요구사항",
  "eval_items": "기술평가(정량적·정성적), 가격평가",
  "price_eval": "협상에 의한 계약 및 절대평가제",
  "eligibility": "NOT_FOUND",
  "system": "NOT_FOUND",
  "integration": "NOT_FOUND",
  "facility": "NOT_FOUND",
  "operation": "NOT_FOUND",
  "fact": "기술 보유업체: ㈜혁",
  "scope": "본 과업은 제한경쟁입찰(협상에 의한 계약) 방식으로 수행되며, 제안요청서에 따른 과업내용을 준수해야 함",
  "procedure": "제안서 제출 → 제안서 평가 → 협상대상자 선정 → 협상 및 계약체결"
}