{
  "project_name": "다층적 융합 학습경험 플랫폼(MILE) 구축",
  "agency": "대전대학교",
  "purpose": "학생 맞춤형 학습 경로 제공 및 학업 성취 향상; 유연한 학사 운영을 통한 융합 교육 활성화",
  "budget": "NOT_FOUND",
  "contract_type": "협상에 의한 계약 (제한경쟁입찰)",
  "deadline": "NOT_FOUND",
  "duration": "하자보증 기간: 본 사업 최종 검수 완료일로부터 최소 12개월 이상",
  "requirements_must": "성능 요구사항(처리 속도 및 시간, 처리량, 동적·정적 용량, 가용성 등); DB 구조 설계; 월별 개발자 포함 PC 보안 체크리스트 제출",
  "eval_items": "기술평가와 가격평가를 실시하여 종합평가 점수 산출; 기술평가: 소프트웨어 기술성 평가기준 적용(조정 가능)",
  "price_eval": "「협상에 의한 계약체결 기준」에 따라 가격평가 점수 산출",
  "eligibility": "소프트웨어사업자(컴퓨터관련서비스사업)로 신고한 자; 「국가를 당사자로 하는 계약에 관한 법률」시행령·시행규칙의 경쟁입찰 참가자격을 갖춘 자; 부정당업자에 해당되지 않는 자; 컨소시엄 구성 시 참여 제한",
  "monitoring_components": "NOT_FOUND",
  "degree_enhancement": "디그리 과정 신청 화면 고도화(디그리 검색, 미이수정보 활용 등); 디그리과정대상자관리 및 미신청이수가능자조회 화면 고도화(과정구분 추가); 나노/마이크로디그리 출력 화면 고도화(과목별 수강 인원현황 출력물 개편); 학점이수정보 화면에 비교과인증제 정보 추가",
  "response_time": "평균 처리시간 요구사항 예시: 0.1초 미만, 1초 미만, 10초 미만, 10초 이상 기준 제시; 오류 응답 메시지: 입력 오류는 10초 이하에 메시지 제시",
  "warranty_period": "최종 검수 완료일로부터 최소 12개월 이상",
  "browser_support": "NOT_FOUND",
  "access_log_retention": "NOT_FOUND",
  "tech_eval_score": "NOT_FOUND",
  "faculty_assessment": "교수역량진단 개편 및 역량 기반 교과 인증 관리 시스템 개편(융합교육 추가)",
  "required_documents": "NOT_FOUND",
  "act_certification": "ACT 교과 인증 강좌개설 화면 연계(교수역량진단 개편 및 역량 기반 교과 인증 관리 시스템 개편 포함)"
}